bn/__init__.py
bn/bn.py
bangla_python-1.9.dist-info/LICENSE
bangla_python-1.9.dist-info/METADATA
bangla_python-1.9.dist-info/WHEEL
bangla_python-1.9.dist-info/top_level.txt
bangla_python-1.9.dist-info/RECORD
