Metadata-Version: 2.1
Name: bangla-python
Version: 1.9
Summary: bangla-python
Author: Nahid Hossain (nahid@cse.uiu.ac.bd)
Author-email: mailbox.nahid@gmail.com
Keywords: bangla-python,bangla language processing,bangla tokenizer,remove bangla punctuation,remove foreign words from bangla text,remove bangla stop words,bangla number to word from text,find bangla numbers from text,bangla to english number conversion,english to bangla number conversion,bangla number to word conversion
Classifier: Development Status :: 4 - Beta
Classifier: Intended Audience :: Developers
Classifier: Programming Language :: Python :: 3
Classifier: Operating System :: Unix
Classifier: Operating System :: MacOS :: MacOS X
Classifier: Operating System :: Microsoft :: Windows
License-File: LICENSE
